mimodulo_he/__init__.py
mimodulo_he-0.1.dist-info/METADATA
mimodulo_he-0.1.dist-info/WHEEL
mimodulo_he-0.1.dist-info/top_level.txt
mimodulo_he-0.1.dist-info/RECORD
